{
  "title": "Enforce Namespace Restrictions",
  "description": "A policy to enforce namespace restriction for NetworkPolicy",
  "difficulty": "Intermediate",
  "time": "5 minutes",
  "details": {
    "steps": [
      {
        "title": "Reason",
        "code": "wait.sh",
        "text": "step1.md"
      },
      {
        "title": "Step 2",
        "text": "step2.md"
      },
      {
        "title": "Step 3",
        "text": "step3.md"
      },
      { 
        "title": "Step 4",
        "text": "step4.md"
      }

    ],
    "intro": {
      "text": "intro.md"
    },
    "finish": {
      "text": "finish.md"
    },
    "assets": {
        "host01": [
            {"file": "template.yaml", "target": "/root/opa/", "chmod": "+x"},
            {"file": "constraint.yaml", "target": "/root/opa/", "chmod": "+x"},
            {"file": "deployment-violation.yaml", "target": "/root/opa/", "chmod": "+x"},
            {"file": "deployment-non-violation.yaml", "target": "/root/opa/", "chmod": "+x"}
        ]
    }
  },
  "environment": {
    "uilayout": "editor-terminal",
    "uieditorpath": "/root/opa"
  },
  "backend": {
    "imageid": "minikube-running"
  }
}
